alttext/__init__.py
alttext/alttext.py
alttext/descengine/bliplocal.py
alttext/descengine/descengine.py
alttext/descengine/googlevertexapi.py
alttext/descengine/replicateapi.py
alttext/langengine/langengine.py
alttext/langengine/openaiapi.py
alttext/langengine/privategpt.py
alttext/ocrengine/ocrengine.py
alttext/ocrengine/tesseract.py
alt_text-0.2.3.dist-info/METADATA
alt_text-0.2.3.dist-info/WHEEL
alt_text-0.2.3.dist-info/licenses/LICENSE
alt_text-0.2.3.dist-info/RECORD
