Metadata-Version: 2.1
Name: alt-text
Version: 0.2.3
Summary: A package used for finding, generating, and setting alt-text for images in HTML and EPUB files.
Project-URL: Source, https://github.com/EbookFoundation/alt-text
Project-URL: PyPi, https://pypi.org/project/alt-text/
Project-URL: Free Ebook Foundation, https://ebookfoundation.org/
Author-email: Free Ebook Foundation <eric@ebookfoundation.org>, Jack Byrne <jbyrne4@stevens.edu>, David Cruz <dcruz2@stevens.edu>, Jared Donnelly <jdonnel3@stevens.edu>, Ethan Kleschinsky <ekleschi@stevens.edu>, Tyler Lane <tlane@stevens.edu>, Carson Lee <clee27@stevens.edu>
Maintainer-email: Eric Hellman <eric@hellman.net>, David Cruz <dcruz2@stevens.edu>
License-File: LICENSE
Classifier: Development Status :: 3 - Alpha
Classifier: Intended Audience :: Developers
Classifier: License :: OSI Approved :: GNU General Public License v3 (GPLv3)
Classifier: Operating System :: OS Independent
Classifier: Programming Language :: Python :: 3
Requires-Python: >=3.7
